[
    {
        "name": "Fastnote",
        "logo": "https://img.backrunner.top/pwp_official/fastnote_logo.png",
        "desc": {
            "zh": "速记便签"
        },
        "link": "https://note.pwp.app"
    },
    {
        "name": "pChecker",
        "logo": "https://img.backrunner.top/pwp_official/pchecker_logo.png",
        "desc": {
            "zh": "文件Hash校验器"
        },
        "link": "https://pchecker.pwp.app"
    },
    {
        "name": "Kuromail",
        "logo": "https://img.backrunner.top/pwp_official/kuromail_logo.png",
        "desc": {
            "zh": "私有企业邮箱"
        },
        "link": "https://www.kuromail.com"
    },
    {
        "name": "Shortlink",
        "logo": "https://img.backrunner.top/pwp_official/shortlink_logo.png",
        "desc": {
            "zh": "短链接平台"
        },
        "link": "https://pwp.link"
    }, {
        "name": "myStats",
        "logo": "https://img.backrunner.top/pwp_official/mystats_logo.png",
        "desc": {
            "zh": "安装量统计"
        },
        "link": "https://mystats.pwp.app"
    }, {
        "name": "Leaf",
        "logo": "https://img.backrunner.top/pwp_official/leaf_logo.png",
        "desc": {
            "zh": "邀请制应用内测平台"
        },
        "link": "https://leaf.pwp.app"
    }, {
        "name": "Pixiv C",
        "logo": "https://img.backrunner.top/pwp_official/pixivc_logo.png",
        "desc": {
            "zh": "技术实验性 Pixiv 图站"
        },
        "link": "https://pixivc.pwp.app"
    }
]
